pymcutil/__init__.py
pymcutil/block/__init__.py
pymcutil/block/block.py
pymcutil/block/block_entity.py
pymcutil/block/block_state.py
pymcutil/command/__init__.py
pymcutil/command/command.py
pymcutil/command/target.py
pymcutil/command/commands/__init__.py
pymcutil/command/commands/_execute_command.py
pymcutil/command/commands/effect_command.py
pymcutil/command/commands/function_command.py
pymcutil/command/commands/say_command.py
pymcutil/command/commands/scoreboard_command.py
pymcutil/command/commands/setblock_command.py
pymcutil/command/commands/effect/__init__.py
pymcutil/command/commands/effect/effect_give_command.py
pymcutil/command/commands/effect/effect_take_command.py
pymcutil/command/commands/execute/__init__.py
pymcutil/command/commands/execute/_execute_conditional_block_mixin.py
pymcutil/command/commands/execute/_execute_conditional_blocks_mixin.py
pymcutil/command/commands/execute/_execute_conditional_entity_mixin.py
pymcutil/command/commands/execute/_execute_if_command.py
pymcutil/command/commands/execute/_execute_store_command.py
pymcutil/command/commands/execute/_execute_unless_command.py
pymcutil/command/commands/execute/execute_as_command.py
pymcutil/command/commands/execute/execute_at_command.py
pymcutil/command/commands/execute/execute_offset_command.py
pymcutil/command/commands/execute/execute_then_command.py
pymcutil/command/commands/execute/if_/__init__.py
pymcutil/command/commands/execute/if_/_execute_if_blocks_command.py
pymcutil/command/commands/execute/if_/execute_if_block_command.py
pymcutil/command/commands/execute/if_/execute_if_entity_command.py
pymcutil/command/commands/execute/if_/blocks/__init__.py
pymcutil/command/commands/execute/if_/blocks/execute_if_blocks_all_command.py
pymcutil/command/commands/execute/if_/blocks/execute_if_blocks_masked_command.py
pymcutil/command/commands/execute/store/__init__.py
pymcutil/command/commands/execute/store/execute_store_result_command.py
pymcutil-0.0.10.dist-info/METADATA
pymcutil-0.0.10.dist-info/RECORD
pymcutil-0.0.10.dist-info/WHEEL
pymcutil-0.0.10.dist-info/top_level.txt
