Metadata-Version: 2.1
Name: pymcutil
Version: 0.0.10
Summary: An expressive Minecraft utility library revolving around data manipulation and generation.
Home-page: https://github.com/Arcensoth/pymcutil
Author: Arcensoth
Author-email: arcensoth@gmail.com
License: MIT
Keywords: minecraft commands library utility datapack data
Platform: UNKNOWN
Classifier: Programming Language :: Python :: 3.6
Classifier: License :: OSI Approved :: MIT License
Classifier: Operating System :: OS Independent
Classifier: Development Status :: 3 - Alpha
Classifier: Intended Audience :: Developers
Requires-Python: >=3.6
